import_funcs.py
linkedlabs.py
variables.py
welcome_page.py
linkedlabs-1.3.2.dist-info/LICENSE.txt
linkedlabs-1.3.2.dist-info/METADATA
linkedlabs-1.3.2.dist-info/WHEEL
linkedlabs-1.3.2.dist-info/top_level.txt
linkedlabs-1.3.2.dist-info/RECORD
