Metadata-Version: 2.1
Name: linkedlabs
Version: 1.3.2
Summary: Get Similar customers (or rows) in data using DNA Matching Algorithms and Artificial Intelligence on your data!
Home-page: http://www.linkedlabs.co
Author: Nashit Babber
Author-email: nashit@linkedlabs.co
License: UNKNOWN
Platform: UNKNOWN
Classifier: Programming Language :: Python :: 3
Classifier: Programming Language :: Python :: 3.6
Classifier: Programming Language :: Python :: 3.7
Classifier: Programming Language :: Python :: 3.8
Classifier: Programming Language :: Python :: 3.9
Classifier: Programming Language :: Python :: 3.10
Classifier: License :: OSI Approved :: GNU General Public License v2 or later (GPLv2+)
Classifier: Operating System :: OS Independent
License-File: LICENSE.txt
Requires-Dist: joblib
Requires-Dist: lightgbm
Requires-Dist: numpy
Requires-Dist: pandas
Requires-Dist: scikit-learn
Requires-Dist: statistics
Requires-Dist: tqdm
Provides-Extra: dev
Requires-Dist: check-manifest ; extra == 'dev'
Requires-Dist: pytest (>=3.7) ; extra == 'dev'
Requires-Dist: twine ; extra == 'dev'
